Workbook

Sheet START HERE
A1: Mentoring Week 2 - SDG-Voted Project Concept Development Workbook
A3: Purpose | B3: Start from shared SDG interest, not from the mentees' original ideas. The group first votes on favorite SDGs, then builds a new project concept from the most-voted SDG base.
A4: Recommended voting rule | B4: Each of the 3 mentees must choose exactly Top 8 favorite SDGs and rank them 1-8. With 17 SDGs, this makes agreement very likely: the chance that at least one SDG is chosen by all 3 is about 90.9%, and at least one SDG gets 2+ votes is effectively 100%.
A5: Why not require unanimity? | B5: Because the mentees are diverse, this workbook now prioritizes high overlap. The group should still use ranking points and the reality check so the final SDG base is not just broad agreement, but also projectable in Japan.
A6: Decision rule | B6: Use the highest vote count first. If tied, use priority points from ranking. If still tied, choose the SDG with the clearest current Japan problem and easiest small pilot.
A7: Week 2 focus | B7: After the base SDG is chosen, develop a project concept: background problem, solution, vision and mission, partners, timeline, budget, target, and task distribution.
A8: Mentor stance | B8: Do not ask whose original idea won. Ask: which SDG do we collectively care about, what problem in Japan is real, and what can 3 mentees realistically build?
A10: Recommended flow
A11: 0-10 min | B11: Explain that original ideas are paused. The group will restart from SDG interest and shared relevance.
A12: 10-25 min | B12: Each mentee ranks Top 8 SDGs privately in W1 SDG Voting.
A13: 25-40 min | B13: Reveal vote summary and identify the top SDG or top SDG cluster using vote count and priority points.
A14: 40-65 min | B14: Use W1 SDG Reality Check to turn top SDGs into Japan-grounded problem options.
A15: 65-90 min | B15: Agree on one SDG base and one problem direction, then continue into Week 2 concept development.

Sheet W1 SDG Voting
A1: Workbook 1 - SDG Preference Voting
A2: Each mentee must choose exactly 8 SDGs. Put 1 for most favorite, 2 for second, up to 8 for eighth. Leave other SDGs blank. This wider vote is intentional because the mentees are diverse and the mentor wants a very high chance of shared SDG agreement.
A4: SDG | B4: Goal name | C4: Japan relevance examples | D4: Faiz rank | E4: Mert rank | F4: Malika rank | G4: Vote count | H4: Priority points | I4: Vote rank | J4: Notes / reason for interest | K4: Sort score
A5: SDG 1 | B5: No Poverty | C5: Poverty prevention, social safety, vulnerable groups | G5: =COUNT(D5:F5) -> 0 | H5: =COUNTIF(D5:F5,1)*8+COUNTIF(D5:F5,2)*7+COUNTIF(D5:F5,3)*6+COUNTIF(D5:F5,4)*5+COUNTIF(D5:F5,5)*4+COUNTIF(D5:F5,6)*3+COUNTIF(D5:F5,7)*2+COUNTIF(D5:F5,8)*1 -> 0 | I5: =RANK(H5,$H$5:$H$21,0) -> 1 | K5: =H5*100+G5*10+(22-ROW())/100 -> 0.17
A6: SDG 2 | B6: Zero Hunger | C6: Food security, nutrition, food loss, local agriculture | G6: =COUNT(D6:F6) -> 0 | H6: =COUNTIF(D6:F6,1)*8+COUNTIF(D6:F6,2)*7+COUNTIF(D6:F6,3)*6+COUNTIF(D6:F6,4)*5+COUNTIF(D6:F6,5)*4+COUNTIF(D6:F6,6)*3+COUNTIF(D6:F6,7)*2+COUNTIF(D6:F6,8)*1 -> 0 | I6: =RANK(H6,$H$5:$H$21,0) -> 1 | K6: =H6*100+G6*10+(22-ROW())/100 -> 0.16
A7: SDG 3 | B7: Good Health and Well-being | C7: Aging, heat safety, mental health, preventive health | G7: =COUNT(D7:F7) -> 0 | H7: =COUNTIF(D7:F7,1)*8+COUNTIF(D7:F7,2)*7+COUNTIF(D7:F7,3)*6+COUNTIF(D7:F7,4)*5+COUNTIF(D7:F7,5)*4+COUNTIF(D7:F7,6)*3+COUNTIF(D7:F7,7)*2+COUNTIF(D7:F7,8)*1 -> 0 | I7: =RANK(H7,$H$5:$H$21,0) -> 1 | K7: =H7*100+G7*10+(22-ROW())/100 -> 0.15
A8: SDG 4 | B8: Quality Education | C8: Youth learning, digital literacy, inclusive education | G8: =COUNT(D8:F8) -> 0 | H8: =COUNTIF(D8:F8,1)*8+COUNTIF(D8:F8,2)*7+COUNTIF(D8:F8,3)*6+COUNTIF(D8:F8,4)*5+COUNTIF(D8:F8,5)*4+COUNTIF(D8:F8,6)*3+COUNTIF(D8:F8,7)*2+COUNTIF(D8:F8,8)*1 -> 0 | I8: =RANK(H8,$H$5:$H$21,0) -> 1 | K8: =H8*100+G8*10+(22-ROW())/100 -> 0.14
A9: SDG 5 | B9: Gender Equality | C9: Equal opportunity, safety, representation | G9: =COUNT(D9:F9) -> 0 | H9: =COUNTIF(D9:F9,1)*8+COUNTIF(D9:F9,2)*7+COUNTIF(D9:F9,3)*6+COUNTIF(D9:F9,4)*5+COUNTIF(D9:F9,5)*4+COUNTIF(D9:F9,6)*3+COUNTIF(D9:F9,7)*2+COUNTIF(D9:F9,8)*1 -> 0 | I9: =RANK(H9,$H$5:$H$21,0) -> 1 | K9: =H9*100+G9*10+(22-ROW())/100 -> 0.13
A10: SDG 6 | B10: Clean Water and Sanitation | C10: Water access, hygiene, disaster sanitation | G10: =COUNT(D10:F10) -> 0 | H10: =COUNTIF(D10:F10,1)*8+COUNTIF(D10:F10,2)*7+COUNTIF(D10:F10,3)*6+COUNTIF(D10:F10,4)*5+COUNTIF(D10:F10,5)*4+COUNTIF(D10:F10,6)*3+COUNTIF(D10:F10,7)*2+COUNTIF(D10:F10,8)*1 -> 0 | I10: =RANK(H10,$H$5:$H$21,0) -> 1 | K10: =H10*100+G10*10+(22-ROW())/100 -> 0.12
A11: SDG 7 | B11: Affordable and Clean Energy | C11: Energy transition, efficiency, renewable literacy | G11: =COUNT(D11:F11) -> 0 | H11: =COUNTIF(D11:F11,1)*8+COUNTIF(D11:F11,2)*7+COUNTIF(D11:F11,3)*6+COUNTIF(D11:F11,4)*5+COUNTIF(D11:F11,5)*4+COUNTIF(D11:F11,6)*3+COUNTIF(D11:F11,7)*2+COUNTIF(D11:F11,8)*1 -> 0 | I11: =RANK(H11,$H$5:$H$21,0) -> 1 | K11: =H11*100+G11*10+(22-ROW())/100 -> 0.11
A12: SDG 8 | B12: Decent Work and Economic Growth | C12: Youth work, aging workforce, labor shortage, gig work | G12: =COUNT(D12:F12) -> 0 | H12: =COUNTIF(D12:F12,1)*8+COUNTIF(D12:F12,2)*7+COUNTIF(D12:F12,3)*6+COUNTIF(D12:F12,4)*5+COUNTIF(D12:F12,5)*4+COUNTIF(D12:F12,6)*3+COUNTIF(D12:F12,7)*2+COUNTIF(D12:F12,8)*1 -> 0 | I12: =RANK(H12,$H$5:$H$21,0) -> 1 | K12: =H12*100+G12*10+(22-ROW())/100 -> 0.1
A13: SDG 9 | B13: Industry, Innovation and Infrastructure | C13: Innovation, resilient infrastructure, digital inclusion | G13: =COUNT(D13:F13) -> 0 | H13: =COUNTIF(D13:F13,1)*8+COUNTIF(D13:F13,2)*7+COUNTIF(D13:F13,3)*6+COUNTIF(D13:F13,4)*5+COUNTIF(D13:F13,5)*4+COUNTIF(D13:F13,6)*3+COUNTIF(D13:F13,7)*2+COUNTIF(D13:F13,8)*1 -> 0 | I13: =RANK(H13,$H$5:$H$21,0) -> 1 | K13: =H13*100+G13*10+(22-ROW())/100 -> 0.09
A14: SDG 10 | B14: Reduced Inequalities | C14: Elderly inclusion, foreign residents, accessibility, regional gaps | G14: =COUNT(D14:F14) -> 0 | H14: =COUNTIF(D14:F14,1)*8+COUNTIF(D14:F14,2)*7+COUNTIF(D14:F14,3)*6+COUNTIF(D14:F14,4)*5+COUNTIF(D14:F14,5)*4+COUNTIF(D14:F14,6)*3+COUNTIF(D14:F14,7)*2+COUNTIF(D14:F14,8)*1 -> 0 | I14: =RANK(H14,$H$5:$H$21,0) -> 1 | K14: =H14*100+G14*10+(22-ROW())/100 -> 0.08
A15: SDG 11 | B15: Sustainable Cities and Communities | C15: Tourism pressure, aging communities, disaster readiness | G15: =COUNT(D15:F15) -> 0 | H15: =COUNTIF(D15:F15,1)*8+COUNTIF(D15:F15,2)*7+COUNTIF(D15:F15,3)*6+COUNTIF(D15:F15,4)*5+COUNTIF(D15:F15,5)*4+COUNTIF(D15:F15,6)*3+COUNTIF(D15:F15,7)*2+COUNTIF(D15:F15,8)*1 -> 0 | I15: =RANK(H15,$H$5:$H$21,0) -> 1 | K15: =H15*100+G15*10+(22-ROW())/100 -> 0.07
A16: SDG 12 | B16: Responsible Consumption and Production | C16: Waste sorting, food loss, sustainable tourism consumption | G16: =COUNT(D16:F16) -> 0 | H16: =COUNTIF(D16:F16,1)*8+COUNTIF(D16:F16,2)*7+COUNTIF(D16:F16,3)*6+COUNTIF(D16:F16,4)*5+COUNTIF(D16:F16,5)*4+COUNTIF(D16:F16,6)*3+COUNTIF(D16:F16,7)*2+COUNTIF(D16:F16,8)*1 -> 0 | I16: =RANK(H16,$H$5:$H$21,0) -> 1 | K16: =H16*100+G16*10+(22-ROW())/100 -> 0.06
... A21: SDG 17 | B21: Partnerships for the Goals | C21: Cross-sector collaboration, youth networks, implementation partnerships | G21: =COUNT(D21:F21) -> 0 | H21: =COUNTIF(D21:F21,1)*8+COUNTIF(D21:F21,2)*7+COUNTIF(D21:F21,3)*6+COUNTIF(D21:F21,4)*5+COUNTIF(D21:F21,5)*4+COUNTIF(D21:F21,6)*3+COUNTIF(D21:F21,7)*2+COUNTIF(D21:F21,8)*1 -> 0 | I21: =RANK(H21,$H$5:$H$21,0) -> 1 | K21: =H21*100+G21*10+(22-ROW())/100 -> 0.01
A23: Voting completeness check
A24: Mentee | B24: Selected SDGs | C24: Must equal | D24: Status | E24: Reminder
A25: Faiz | B25: =COUNT(D5:D21) -> 0 | C25: 8 | D25: =IF(B25=C25,"Complete","Fix selection count") -> Fix selection count | E25: Choose exactly 8 SDGs. Ranking must use 1-8, no duplicates inside the same mentee column.
A26: Mert | B26: =COUNT(E5:E21) -> 0 | C26: 8 | D26: =IF(B26=C26,"Complete","Fix selection count") -> Fix selection count | E26: Choose exactly 8 SDGs. Ranking must use 1-8, no duplicates inside the same mentee column.
A27: Malika | B27: =COUNT(F5:F21) -> 0 | C27: 8 | D27: =IF(B27=C27,"Complete","Fix selection count") -> Fix selection count | E27: Choose exactly 8 SDGs. Ranking must use 1-8, no duplicates inside the same mentee column.
A29: Top 8 rationale
A30: Top 8 is mandatory because the mentees' interests are diverse and the mentoring goal is to find a shared SDG base before discussing project ideas. Probability check: if each of 3 mentees chooses 8 out of 17 SDGs, the chance that at least one SDG is chosen by all 3 is about 90.9%, while the chance that at least one SDG receives 2+ votes is effectively 100%. Use the vote summary, then narrow with the SDG Reality Check so the final project is still specific and realistic.

Sheet W1 SDG Reality Check
A1: Workbook 1 - SDG Reality Check: Turn Top SDGs into Projectable Problems
A2: Use this after Top 8 voting. Because Top 8 creates broad overlap, the reality check is essential: convert the most-voted SDG(s) into one Japan-specific problem that can become a realistic Week 2 project.
A4: Top SDG option | B4: Japan-specific problem option | C4: Possible beneficiary | D4: Small feasible project format | E4: Evidence / validation needed
A12: Reality gates before moving to Week 2
A13: Gate | B13: Problem Option A | C13: Problem Option B | D13: Problem Option C | E13: What passing looks like
A14: Is the problem current in Japan? | E14: There is a credible source, observation, or stakeholder signal.
A15: Is the beneficiary reachable? | E15: The team can reach, survey, interview, or clearly define them.
A16: Can 3 mentees build a small output? | E16: Workshop, toolkit, campaign kit, policy brief, prototype, or partner map.
A17: Can the project be explained simply? | E17: Problem-solution-impact can be told in under 60 seconds.
A18: Can impact be measured? | E18: Output and outcome metrics can be named.
A19: Does it fit the top-voted SDG? | E19: The SDG is causal, not decorative.
A20: Should this move to Week 2? | E20: Yes / Needs validation / No.
A22: Japan problem prompts by common SDG cluster
A23: SDG cluster | B23: Japan situation to explore | C23: Possible project format | D23: Evidence source to start | E23: Mentor caution
A24: SDG 3 + 11 + 13 | B24: Heat safety, disaster readiness, elderly support, community preparedness. | C24: Community heat/disaster readiness toolkit or mini workshop. | D24: MoE/JMA heat alert info; local municipal guidance. | E24: Avoid broad disaster policy; make it daily-life practical.
A25: SDG 8 + 4 + 10 | B25: Youth work readiness, AI/gig-work risks, foreign resident inclusion, aging workforce. | C25: Decent-work literacy module or youth toolkit. | D25: Cabinet Office aging report; labor-related official sources. | E25: Avoid only writing an essay; create a usable module.
A26: SDG 7 + 8 + 13 | B26: Green transition, GX finance, SME decarbonization literacy. | C26: Transition finance explainer or SME/youth awareness kit. | D26: METI transition finance and GX materials. | E26: Avoid technical bank modeling beyond student capacity.
A27: SDG 11 + 12 + 17 | B27: Tourism pressure, waste sorting, resident comfort, visitor behavior. | C27: Sustainable visitor etiquette campaign kit. | D27: JNTO visitor arrivals; local tourism guidance. | E27: Avoid generic tourism slogans; target one behavior.

Sheet W1 Vote Summary
A1: Workbook 1 - Vote Summary and SDG Base Selection
A2: This summarizes the mandatory Top 8 SDG vote and records the SDG base that will drive Week 2 project development.
A4: Summary item | B4: Top 1 | C4: Top 2 | D4: Top 3 | E4: Notes
A5: SDG | B5: =INDEX('W1 SDG Voting'!$A$5:$A$21,MATCH(LARGE('W1 SDG Voting'!$K$5:$K$21,1),'W1 SDG Voting'!$K$5:$K$21,0)) -> SDG 1 | C5: =INDEX('W1 SDG Voting'!$A$5:$A$21,MATCH(LARGE('W1 SDG Voting'!$K$5:$K$21,2),'W1 SDG Voting'!$K$5:$K$21,0)) -> SDG 2 | D5: =INDEX('W1 SDG Voting'!$A$5:$A$21,MATCH(LARGE('W1 SDG Voting'!$K$5:$K$21,3),'W1 SDG Voting'!$K$5:$K$21,0)) -> SDG 3 | E5: If tied, check vote count first, then priority points, then Japan problem feasibility. With Top 8, ties are possible because the vote is intentionally broad.
A6: Goal name | B6: =INDEX('W1 SDG Voting'!$B$5:$B$21,MATCH(LARGE('W1 SDG Voting'!$K$5:$K$21,1),'W1 SDG Voting'!$K$5:$K$21,0)) -> No Poverty | C6: =INDEX('W1 SDG Voting'!$B$5:$B$21,MATCH(LARGE('W1 SDG Voting'!$K$5:$K$21,2),'W1 SDG Voting'!$K$5:$K$21,0)) -> Zero Hunger | D6: =INDEX('W1 SDG Voting'!$B$5:$B$21,MATCH(LARGE('W1 SDG Voting'!$K$5:$K$21,3),'W1 SDG Voting'!$K$5:$K$21,0)) -> Good Health and Well-being
A7: Vote count | B7: =INDEX('W1 SDG Voting'!$G$5:$G$21,MATCH(LARGE('W1 SDG Voting'!$K$5:$K$21,1),'W1 SDG Voting'!$K$5:$K$21,0)) -> 0 | C7: =INDEX('W1 SDG Voting'!$G$5:$G$21,MATCH(LARGE('W1 SDG Voting'!$K$5:$K$21,2),'W1 SDG Voting'!$K$5:$K$21,0)) -> 0 | D7: =INDEX('W1 SDG Voting'!$G$5:$G$21,MATCH(LARGE('W1 SDG Voting'!$K$5:$K$21,3),'W1 SDG Voting'!$K$5:$K$21,0)) -> 0
A8: Priority points | B8: =INDEX('W1 SDG Voting'!$H$5:$H$21,MATCH(LARGE('W1 SDG Voting'!$K$5:$K$21,1),'W1 SDG Voting'!$K$5:$K$21,0)) -> 0 | C8: =INDEX('W1 SDG Voting'!$H$5:$H$21,MATCH(LARGE('W1 SDG Voting'!$K$5:$K$21,2),'W1 SDG Voting'!$K$5:$K$21,0)) -> 0 | D8: =INDEX('W1 SDG Voting'!$H$5:$H$21,MATCH(LARGE('W1 SDG Voting'!$K$5:$K$21,3),'W1 SDG Voting'!$K$5:$K$21,0)) -> 0
A10: Final SDG base for project
A11: Selected base SDG
A12: Optional supporting SDG 1
A13: Optional supporting SDG 2
A14: Why this SDG base was selected
A15: Japan problem direction
A16: Beneficiary direction
A17: Small project format
A19: Fallback rules
A20: If many SDGs are tied, group them into a practical SDG cluster, then choose the cluster with the clearest Japan problem and smallest feasible project format.
A21: Do not use all winning SDGs. Select one base SDG and at most two supporting SDGs for clarity.
A22: Do not return to original idea ownership unless the idea clearly fits the selected SDG base.

Sheet W1 SDG Consensus
A1: Workbook 1 - SDG Consensus Record
A3: Selected base SDG
A4: Supporting SDG(s), if any
A5: Winning vote evidence | B5: Record vote count and priority points from W1 Vote Summary. Note that each mentee ranked exactly 8 SDGs.
A6: Agreed Japan problem statement | B6: In Japan, [beneficiary] faces [problem] because [cause/context].
A7: Why original ideas are paused | B7: The group is starting from the shared SDG base instead of selecting one member's original idea.
A8: Project direction in one sentence | B8: For [beneficiary] in Japan, we will create [small project output] to improve [measurable outcome].
A9: Validation needed before Week 3
A10: Final decision date
A11: Group agreement statement | B11: We agree to build one group project from the selected SDG base and not campaign for individual original ideas unless they fit the shared SDG direction.
A13: Mentee sign-off
A14: Name | B14: Top SDG they voted for | C14: I accept the shared SDG base | D14: Concern still open? | E14: Role in Week 2
A15: Faiz Abdillah
A16: Mert Bian
A17: Malika

Sheet W2 Concept Canvas
A1: Workbook 2 - Project Concept Canvas from Selected SDG Base
A2: Use this after the group selects the base SDG from the mandatory Top 8 vote. Since the vote is broad, keep the project narrow: one base SDG, at most two supporting SDGs, one Japan-specific problem, one realistic small solution.
A4: Concept element | B4: Group answer | C4: Mentor prompt
A5: Selected base SDG | C5: Pull from W1 Vote Summary / W1 SDG Consensus.
A6: Supporting SDG(s) | C6: Use only if they sharpen the project. Avoid listing too many.
A7: Japan problem statement | C7: In Japan, [specific beneficiary] faces [problem] because [cause/current condition].
A8: Why the problem matters now | C8: Use current Japan evidence, policy, demographic, climate, tourism, labor, or community context.
A9: Target beneficiaries | C9: Specific reachable people or institutions, not society in general.
A10: Proposed small solution | C10: Workshop, toolkit, campaign kit, policy brief, prototype, guide, partner map, or awareness module.
A11: Core activities | C11: List 3-5 concrete actions the team can execute before the presentation.
A12: Vision | C12: Long-term future if this SDG problem is addressed.
A13: Mission | C13: What this project does now within summit capacity.
A14: Potential partners | C14: University clubs, local NPOs, community centers, municipal offices, SMEs, tourism centers, online communities.
A15: Expected outputs | C15: Tangible outputs: toolkit, deck, survey, partner list, proposal, PPT, prototype.
A16: Expected outcomes | C16: Measurable change: awareness score, validation response, number reached, usability feedback.
... A20: Decision before Week 3 | C20: What must be locked before drafting proposal and PPT?

Sheet W2 SDG & 5W1H
A1: Workbook 2 - Selected SDG Alignment and 5W1H Problem Development
A3: A. From SDG label to real problem
A4: Question | B4: Group answer | C4: Quality check | D4: Japan example prompt
A5: What SDG was selected? | C5: Base SDG is clear; supporting SDGs are limited to avoid a vague project. | D5: Example: SDG 8 as base, SDG 4 and 10 as support. Do not use all voted SDGs.
A6: What is the problem? | C6: Specific problem, not only an SDG theme. | D6: Not 'decent work'. Better: youth/foreign students lack practical literacy about job insecurity and work rights.
A7: Why does it occur? | C7: Names root causes the project can influence. | D7: Information is scattered, too technical, not youth-friendly, or not localized.
A8: Who is affected? | C8: Specific reachable beneficiary. | D8: Youth, foreign residents, elderly residents, SMEs, tourists, local communities.
A9: Where does it occur? | C9: Place/context in Japan. | D9: University community, urban tourist district, local community center, SME context, online job platform.
A10: When is it most visible? | C10: Situation/time trigger. | D10: Job search, heat season, tourist peak season, disaster alerts, transition planning.
A11: How does it look now? | C11: Observable current condition. | D11: Official information exists, but it is scattered, technical, language-heavy, or not actionable.
A13: B. SDG causal alignment
A14: SDG / Target | B14: Why this target fits | C14: Project activity that addresses it | D14: Indicator / evidence
A21: C. Theory of change
A22: Inputs | B22: Activities | C22: Outputs | D22: Outcomes

Sheet W2 Partners Timeline Budget
A1: Workbook 2 - Partners, Timeline, and Budget Draft
A3: A. Potential Partner Map
A4: Partner type | B4: Example in Japan | C4: Why useful | D4: Contact/access path | E4: Owner | F4: Next step
A5: University / student club | B5: Japan Youth Summit network or host university club | C5: Access to youth participants and peer feedback
A6: Local NPO / community center | B6: Community center, senior support NPO, multicultural center | C6: Access to community needs and cultural validation
A7: Municipal / public office | B7: City SDGs, tourism, environment, or labor-related desk | C7: Policy context and credibility
A8: Private sector / SME group | B8: Local SME association, tourism business, green finance stakeholder | C8: Real-world constraints and possible continuation
A9: Information source partner | B9: JNTO, METI, Cabinet Office, MoE/JMA official data | C9: Evidence, not direct implementation
A11: B. Timeline to Week 5 Presentation
A12: Period | B12: Milestone | C12: Deliverable | D12: Owner | E12: Status | F12: Risk / dependency
A13: Week 2 session | B13: Finalize concept | C13: Completed canvas + SDG alignment + task split | E13: Not started
A14: Within 48 hours | B14: Validate weak assumptions | C14: Evidence notes, partner/contact list, revised problem statement | E14: Not started
A15: Before Week 3 | B15: Build first draft | C15: Proposal outline + PPT skeleton | E15: Not started
A16: Week 3 | B16: Draft development review | C16: Draft proposal with logical problem-to-solution flow | E16: Not started
A17: Week 4 | B17: Refinement and readiness | C17: Improved proposal quality and presentation design | E17: Not started
A18: Week 5 | B18: Simulation and finalization | C18: Final proposal + PPT + presentation role distribution | E18: Not started
A20: C. Budget Draft
A21: Cost item | B21: Needed for | C21: Unit cost (JPY) | D21: Quantity | E21: Estimated total (JPY) | F21: Low-cost alternative
A22: Printing / handouts | B22: Workshop/toolkit/campaign material | E22: =C22*D22 -> 0 | F22: Digital PDF or QR code
A23: Local transport | B23: Partner visit / field observation | E23: =C23*D23 -> 0 | F23: Online interview or nearby site
A24: Venue / room | B24: Small workshop or discussion | E24: =C24*D24 -> 0 | F24: University room/community free space
A25: Translation / design support | B25: Bilingual clarity and professional visuals | E25: =C25*D25 -> 0 | F25: Peer review + simple templates
A26: Materials / stationery | B26: Workshop activity | E26: =C26*D26 -> 0 | F26: Use available materials
A27: Contingency | B27: Unexpected minor costs | E27: =C27*D27 -> 0 | F27: Limit scope
D28: Total | E28: =SUM(E22:E27) -> 0

Sheet W2 Tasks & Checklist
A1: Workbook 2 - Task Distribution and Mentor Checklist
A3: A. Task Distribution Before Week 3
A4: Mentee | B4: Task / research area | C4: Why it matters | D4: Due date | E4: Status | F4: Notes / mentor reminder
A5: Faiz Abdillah | B5: Evidence and feasibility lead for selected SDG | C5: Find current Japan evidence, estimate budget/resources, and test whether the project format is realistic. | E5: Not started
A6: Mert Bian | B6: Problem framing and SDG logic lead | C6: Turn the selected SDG into a clear problem-solution-impact narrative. | E6: Not started
A7: Malika | B7: Beneficiary and communication lead | C7: Clarify target audience, partner path, survey/interview questions, and presentation clarity. | E7: Not started
A8: All members | B8: Shared SDG project agreement | C8: Keep the project based on the selected SDG, not individual original idea ownership. | E8: Not started
A10: B. Week 2 Mentor Checklist
A11: Check | B11: Done? | C11: Evidence / note | D11: Owner | E11: Issue? | F11: Follow-up
A12: Each mentee selected exactly 8 SDGs | D12: Mentor
A13: Vote summary identified top SDG or SDG cluster | D13: Mentor
A14: Original ideas were paused before project selection | D14: Mentor
A15: Selected SDG has a Japan-specific problem direction | D15: Group
A16: Beneficiary is specific and reachable | D16: Group
A17: Small project format is realistic | D17: Group
A18: Evidence or validation task is assigned | D18: Group
A19: Vision and mission are drafted | D19: Group
A20: Potential partners are listed | D20: Group
A21: Timeline and budget draft exist | D21: Group
A22: Group leader will submit WhatsApp summary | D22: Group leader
A23: Tasks before Week 3 assigned | D23: Mentor + group

Sheet Japan Evidence Bank
A1: Japan Evidence Bank - Current Context for Examples and Validation
A3: Theme | B3: Current Japan context to consider | C3: Useful for which idea? | D3: Source URL / note
A4: Aging society | B4: Japan's Cabinet Office FY2025 aging report states that as of Oct. 1, 2024 Japan had 36.24 million people aged 65+, equal to 29.3% of the population. | C4: Ideas involving elderly inclusion, labor, welfare, heat safety, digital access. | D4: Cabinet Office, Annual Report on the Ageing Society FY2025: https://www8.cao.go.jp/kourei/english/annualreport/2025/pdf/2025.pdf
A5: Elderly living alone | B5: The same report notes that people aged 65+ living alone are increasing, with 2020 shares of 15.0% for men and 22.1% for women, projected higher by 2050. | C5: Social isolation, community support, heat safety, digital or service access. | D5: Cabinet Office, Annual Report on the Ageing Society FY2025: https://www8.cao.go.jp/kourei/english/annualreport/2025/pdf/2025.pdf
A6: Inbound tourism | B6: JNTO reported 3,618,900 visitor arrivals to Japan in March 2026, with Jan-Mar 2026 arrivals at 10,683,500. | C6: Sustainable tourism, multilingual guidance, visitor behavior, community strain. | D6: JNTO press release Apr. 15, 2026: https://www.jnto.go.jp/en/news/20260415.pdf
A7: Heat illness | B7: Japan's 2026 Heat Stroke Alert operation starts Apr. 22, 2026. Alerts are issued when WBGT is forecast at 33 or higher and encourage protective actions, including checking on elderly people. | C7: Climate action, disaster readiness, elderly safety, public health workshops. | D7: Ministry of the Environment / JMA heat illness site: https://www.wbgt.env.go.jp/en/sp/alert.php
A8: Green transition finance | B8: METI states that more than 150 trillion yen of public-private investment is required over the next 10 years for GX investment, and Japan decided to issue 20 trillion yen of GX Economy Transition Bonds. | C8: Faiz's green credit / transition finance idea; SDG 7, 8, 13. | D8: METI Transition Finance: https://www.meti.go.jp/english/policy/energy_environment/transition_finance/index.html
A9: Transition finance credibility | B9: METI frames transition finance as supporting companies that steadily reduce GHG emissions according to long-term strategies for a decarbonized society. | C9: Green credit literacy, SME decarbonization, finance education, policy brief. | D9: METI Transition Finance: https://www.meti.go.jp/english/policy/energy_environment/transition_finance/index.html
A10: Decent work and aging | B10: Cabinet Office FY2025 report notes employment among people aged 65+ has continued increasing and elderly willingness to work is growing. | C10: Mert's SDG 8 decent work idea; aging workforce, work rights, lifelong employment. | D10: Cabinet Office, Annual Report on the Ageing Society FY2025: https://www8.cao.go.jp/kourei/english/annualreport/2025/pdf/2025.pdf
A11: Program requirements | B11: Mentor handbook Week 2 asks for concept development: background problem, solution, vision and mission, partners, timeline, budget draft, target and task distribution. | C11: All ideas; confirms what Week 2 output must include. | D11: Local file: Mentor Handbook.pdf

Sheet Rubric Guide
A1: Rubric Guide - From SDG Vote to Real Project
A3: Check | B3: Weak | C3: Acceptable | D3: Strong
A4: SDG selection | B4: Chosen because one person insists. | C4: Chosen by vote but still broad. | D4: Chosen through mandatory Top 8 vote with clear top rank or cluster and group acceptance.
A5: Japan problem | B5: Only names an SDG theme. | C5: Names a Japan issue but evidence is still thin. | D5: Specific current Japan problem with source or validation path.
A6: Beneficiary | B6: Society, youth, or community in general. | C6: Beneficiary named but access unclear. | D6: Specific reachable beneficiary and context.
A7: Project format | B7: Large policy change, institutional reform, or abstract awareness. | C7: Small format exists but activities need detail. | D7: Small deliverable can be built by 3 mentees before presentation.
A8: Evidence | B8: Opinion or general internet claim. | C8: One credible source. | D8: Credible source plus stakeholder signal, observation, or fast validation plan.
A9: Team dynamics | B9: Original idea competition continues. | C9: Group accepts vote but roles are uneven. | D9: Roles are assigned around the shared SDG project.
A10: Week 2 readiness | B10: No clear concept yet. | C10: Concept exists but needs narrowing. | D10: Problem, solution, partners, timeline, budget, and tasks can be drafted.
A12: Recommended rule
A13: Each mentee chooses Top 8 SDGs. Select the SDG with the highest vote count, then priority points. Because Top 8 is broad, the group must narrow to one base SDG and at most two supporting SDGs before Week 2 concept development.
